lady/__init__.py
lady/cli.py
lady/lady.py
lady-0.1.0.dist-info/AUTHORS.rst
lady-0.1.0.dist-info/LICENSE
lady-0.1.0.dist-info/METADATA
lady-0.1.0.dist-info/WHEEL
lady-0.1.0.dist-info/entry_points.txt
lady-0.1.0.dist-info/top_level.txt
lady-0.1.0.dist-info/RECORD
