Metadata-Version: 2.1
Name: lady
Version: 0.1.0
Summary: Python package that generates clean, responsive HTML e-mails for sending transactional mail
Home-page: https://github.com/TaceyWong/lady
Author: Tacey Wong
Author-email: xinyong.w@gmail.com
License: MIT license
Keywords: lady
Platform: UNKNOWN
Classifier: Development Status :: 2 - Pre-Alpha
Classifier: Intended Audience :: Developers
Classifier: License :: OSI Approved :: MIT License
Classifier: Natural Language :: English
Classifier: Programming Language :: Python :: 3
Classifier: Programming Language :: Python :: 3.6
Classifier: Programming Language :: Python :: 3.7
Classifier: Programming Language :: Python :: 3.8
Requires-Python: >=3.6
Requires-Dist: Click (>=7.0)
